cdk_ecr_deployment/__init__.py
cdk_ecr_deployment/py.typed
cdk_ecr_deployment/_jsii/__init__.py
cdk_ecr_deployment/_jsii/cdk-ecr-deployment@4.0.6.jsii.tgz
cdk_ecr_deployment-4.0.6.dist-info/LICENSE
cdk_ecr_deployment-4.0.6.dist-info/METADATA
cdk_ecr_deployment-4.0.6.dist-info/NOTICE
cdk_ecr_deployment-4.0.6.dist-info/WHEEL
cdk_ecr_deployment-4.0.6.dist-info/top_level.txt
cdk_ecr_deployment-4.0.6.dist-info/RECORD
